cache_on_disk/__init__.py
cache_on_disk/cache.py
cache_on_disk-0.5.0.dist-info/METADATA
cache_on_disk-0.5.0.dist-info/WHEEL
cache_on_disk-0.5.0.dist-info/top_level.txt
cache_on_disk-0.5.0.dist-info/RECORD
