Metadata-Version: 2.4
Name: cache_on_disk
Version: 0.5.0
Summary: A disk-based caching utility for Python functions
Author-email: Niels Warncke <niels.warncke@gmail.com>
License: MIT
Project-URL: Homepage, https://github.com/nielsrolf/dcache
Project-URL: Bug Tracker, https://github.com/nielsrolf/dcache/issues
Classifier: Programming Language :: Python :: 3
Classifier: License :: OSI Approved :: MIT License
Classifier: Operating System :: OS Independent
Requires-Python: >=3.7
Requires-Dist: diskcache>=5.0.0
